SevenSegDisplayHEX/HextoSevenSegment.v
module HextoSevenSegment (
    input [3:0] number, 
    input dp,
    output reg [7:0] sseg
);

// Seven Segment Format 
// ---a---
// f     b 
// |_ g _|
// e     c
// ---d---  dp
// sseg format: dp,a,b,c,d,e,f,g (bit 7 to 0)

always @* begin
    case (number)
        // Active Low values
        4'h0: sseg[6:0] = 7'b0000001;
        4'h1: sseg[6:0] = 7'b1001111;
        4'h2: sseg[6:0] = 7'b0010010;
        4'h3: sseg[6:0] = 7'b0000110;
        4'h4: sseg[6:0] = 7'b1001100;
        4'h5: sseg[6:0] = 7'b0100100;
        4'h6: sseg[6:0] = 7'b0100000;
        4'h7: sseg[6:0] = 7'b0001111;
        4'h8: sseg[6:0] = 7'b0000000;
        4'h9: sseg[6:0] = 7'b0000100;
        4'hA: sseg[6:0] = 7'b0001000;
        4'hB: sseg[6:0] = 7'b1100000;
        4'hC: sseg[6:0] = 7'b0110001;
        4'hD: sseg[6:0] = 7'b1000010;
        4'hE: sseg[6:0] = 7'b0110000;
        4'hF: sseg[6:0] = 7'b0111000;
        default: sseg[6:0] = 7'b1111111; // all segments off (active-low)
    endcase
    sseg[7] = ~dp; // Active-low DP (invert logic if needed)
end

endmodule

SevenSegDisplayHEX/tb_HextoSevenSegment.v
`timescale 1ns / 1ps
`include "HextoSevenSegment.v"

module tb_HextoSevenSegment;

reg [3:0] number;
reg dp;
wire [7:0] sseg;


HextoSevenSegment SSD(.number(number), .dp(dp), .sseg(sseg));

initial
begin 

$dumpfile("tb_HextoSevenSegment.vcd");
$dumpvars(0, tb_HextoSevenSegment);

number = 4'b0;
dp = 1'b0;


#10 number = 4'h1;
#10 number = 4'h2;
#10 number = 4'h3;
#10 number = 4'h4;
#10 number = 4'h5;
#10 number = 4'h6;
#10 number = 4'h7;
#10 number = 4'h8;
#10 number = 4'h9;
#10 number = 4'ha;
#10 number = 4'hb;
#10 number = 4'hc;
#10 number = 4'hd;
#10 number = 4'he;

$display("%b",sseg);
end 

endmodule

SevenSegDisplayHEX/tb_HextoSevenSegment.vcd
$date
	Fri Jul 11 22:06:51 2025
$end
$version
	Icarus Verilog
$end
$timescale
	1ps
$end
$scope module tb_HextoSevenSegment $end
$var wire 8 ! sseg [7:0] $end
$var reg 1 " dp $end
$var reg 4 # number [3:0] $end
$scope module SSD $end
$var wire 1 " dp $end
$var wire 4 $ number [3:0] $end
$var reg 8 % sseg [7:0] $end
$upscope $end
$upscope $end
$enddefinitions $end
$comment Show the parameter values. $end
$dumpall
$end
#0
$dumpvars
b10000001 %
b0 $
b0 #
0"
b10000001 !
$end
#10000
b11001111 !
b11001111 %
b1 #
b1 $
#20000
b10010010 !
b10010010 %
b10 #
b10 $
#30000
b10000110 !
b10000110 %
b11 #
b11 $
#40000
b11001100 !
b11001100 %
b100 #
b100 $
#50000
b10100100 !
b10100100 %
b101 #
b101 $
#60000
b10100000 !
b10100000 %
b110 #
b110 $
#70000
b10001111 !
b10001111 %
b111 #
b111 $
#80000
b10000000 !
b10000000 %
b1000 #
b1000 $
#90000
b10000100 !
b10000100 %
b1001 #
b1001 $
#100000
b10001000 !
b10001000 %
b1010 #
b1010 $
#110000
b11100000 !
b11100000 %
b1011 #
b1011 $
#120000
b10110001 !
b10110001 %
b1100 #
b1100 $
#130000
b11000010 !
b11000010 %
b1101 #
b1101 $
#140000
b10110000 !
b10110000 %
b1110 #
b1110 $
